dyce/__init__.py
dyce/_version.py
dyce/evaluation.py
dyce/h.py
dyce/lifecycle.py
dyce/p.py
dyce/py.typed
dyce/r.py
dyce/rng.py
dyce/types.py
dyce-0.6.2.dist-info/LICENSE
dyce-0.6.2.dist-info/METADATA
dyce-0.6.2.dist-info/WHEEL
dyce-0.6.2.dist-info/top_level.txt
dyce-0.6.2.dist-info/RECORD
