Metadata-Version: 2.1
Name: dyce
Version: 0.6.2
Summary: Simple Python tools for exploring dice outcomes and other finite discrete probabilities
Home-page: https://posita.github.io/dyce/
Author: Matt Bogosian
Author-email: matt@bogosian.net
License: MIT License
Project-URL: Source Repository, https://github.com/posita/dyce/
Classifier: Topic :: Education
Classifier: Topic :: Games/Entertainment
Classifier: Topic :: Scientific/Engineering :: Mathematics
Classifier: Topic :: Software Development :: Libraries :: Python Modules
Classifier: Typing :: Typed
Classifier: Development Status :: 4 - Beta
Classifier: Intended Audience :: Developers
Classifier: Intended Audience :: Education
Classifier: Intended Audience :: Science/Research
Classifier: License :: OSI Approved :: MIT License
Classifier: Operating System :: OS Independent
Classifier: Programming Language :: Python
Classifier: Programming Language :: Python :: 3.9
Classifier: Programming Language :: Python :: 3.10
Classifier: Programming Language :: Python :: 3.11
Classifier: Programming Language :: Python :: Implementation :: CPython
Classifier: Programming Language :: Python :: Implementation :: PyPy
Requires-Python: >=3.9
License-File: LICENSE
Requires-Dist: numerary (~=0.4.3)
Provides-Extra: dev
Requires-Dist: numpy ; extra == 'dev'
Requires-Dist: pandas ; extra == 'dev'
Requires-Dist: pre-commit ; extra == 'dev'
Requires-Dist: sympy (~=1.9) ; extra == 'dev'
Requires-Dist: tox (~=4.0) ; extra == 'dev'
Requires-Dist: versioningit (~=2.0) ; extra == 'dev'
